<?xml version="1.0" encoding="UTF-8" ?>
<cacheXmlBean>
    <cacheBeans>
        <entry>
            <key>findById</key>
            <value>
                <cacheBean >
                    <expireTime>10</expireTime>

                </cacheBean>
            </value>
        </entry>
        <entry>
            <key>selectAll</key>
            <value>
                <cacheBean >
                    <expireTime>10</expireTime>
                </cacheBean>
            </value>
        </entry>

    </cacheBeans>
</cacheXmlBean>
